{"results":[{"gender":"male","name":{"title":"Mr","first":"Nicolay","last":"Svenning"},"location":{"street":{"number":7897,"name":"Henriks vei"},"city":"Øyenkilen","state":"Sør-Trøndelag","country":"Norway","postcode":"5812","coordinates":{"latitude":"54.5150","longitude":"-2.0687"},"timezone":{"offset":"-2:00","description":"Mid-Atlantic"}},"email":"nicolay.svenning@example.com","login":{"uuid":"bd6c5fbf-603a-46f7-8316-bc72234b9e60","username":"beautifulkoala740","password":"christy","salt":"zbpPA9EG","md5":"1ded59bd65b148325e61e2b0900c3ada","sha1":"e3be74f83dba967bb9464e23dc49f0b3918316be","sha256":"cc292b3a76a127c1d842fac26fb4fe8e833a4ca590c67034247443357b57f35f"},"dob":{"date":"1987-09-24T00:51:42.565Z","age":34},"registered":{"date":"2009-12-24T16:26:14.493Z","age":12},"phone":"22275840","cell":"93807460","id":{"name":"FN","value":"24098749515"},"picture":{"large":"https://randomuser.me/api/portraits/men/12.jpg","medium":"https://randomuser.me/api/portraits/med/men/12.jpg","thumbnail":"https://randomuser.me/api/portraits/thumb/men/12.jpg"},"nat":"NO"},{"gender":"female","name":{"title":"Mrs","first":"Osnaura","last":"Novaes"},"location":{"street":{"number":5868,"name":"Rua Piauí "},"city":"Passos","state":"Roraima","country":"Brazil","postcode":66700,"coordinates":{"latitude":"52.0428","longitude":"-57.3141"},"timezone":{"offset":"+3:00","description":"Baghdad, Riyadh, Moscow, St. Petersburg"}},"email":"osnaura.novaes@example.com","login":{"uuid":"d0c7b00a-1ccb-4989-8ada-8434c6f44965","username":"organickoala395","password":"domino","salt":"IslqVy9r","md5":"d20a9708edfcd2faee438dab1a26c0b6","sha1":"4a351e11cc5f6d3b8d7e850872eda56cf9852214","sha256":"f53a8ee1cecfab663ae80eb7933389c4ec4eac6db8a0294fe042abf6f05dea2f"},"dob":{"date":"1997-03-03T05:40:29.300Z","age":24},"registered":{"date":"2009-08-03T15:19:02.347Z","age":12},"phone":"(78) 5417-1895","cell":"(97) 1578-0964","id":{"name":"","value":null},"picture":{"large":"https://randomuser.me/api/portraits/women/63.jpg","medium":"https://randomuser.me/api/portraits/med/women/63.jpg","thumbnail":"https://randomuser.me/api/portraits/thumb/women/63.jpg"},"nat":"BR"},{"gender":"male","name":{"title":"Mr","first":"Toivo","last":"Waisanen"},"location":{"street":{"number":5283,"name":"Korkeavuorenkatu"},"city":"Ristiina","state":"Satakunta","country":"Finland","postcode":95558,"coordinates":{"latitude":"84.7466","longitude":"-28.4974"},"timezone":{"offset":"+10:00","description":"Eastern Australia, Guam, Vladivostok"}},"email":"toivo.waisanen@example.com","login":{"uuid":"acd973b1-ee8f-4b28-8e0e-a764eff85baf","username":"smallswan542","password":"thomas","salt":"lgMfxMCL","md5":"b0ab1473426420b4c93899d297fcc3c7","sha1":"3235aa6135005373cd5b7436a9464e3eed1e8a19","sha256":"33f904dfc47644d1682a8918e015e228374b55940c6cdcd10e8145be71120574"},"dob":{"date":"1987-12-26T11:26:13.748Z","age":34},"registered":{"date":"2005-09-15T22:38:14.535Z","age":16},"phone":"03-083-763","cell":"045-576-23-32","id":{"name":"HETU","value":"NaNNA659undefined"},"picture":{"large":"https://randomuser.me/api/portraits/men/81.jpg","medium":"https://randomuser.me/api/portraits/med/men/81.jpg","thumbnail":"https://randomuser.me/api/portraits/thumb/men/81.jpg"},"nat":"FI"},{"gender":"female","name":{"title":"Mrs","first":"Zenna","last":"Van Domselaar"},"location":{"street":{"number":2061,"name":"Bakkerijstraat"},"city":"Krommenie","state":"Utrecht","country":"Netherlands","postcode":93301,"coordinates":{"latitude":"-55.7005","longitude":"-144.9403"},"timezone":{"offset":"+3:00","description":"Baghdad, Riyadh, Moscow, St. Petersburg"}},"email":"zenna.vandomselaar@example.com","login":{"uuid":"916a79ec-d7c3-4d31-a5b9-688ca4553a8d","username":"sadbird131","password":"starcraf","salt":"DBC9Nc7L","md5":"4009a9b3134c395ccf6ae7ea25c5c3b9","sha1":"b1219c8d9c23c943c8abdcf0af146ebe333d53ab","sha256":"ea168c3137a1d6af7d87752e18b6a3becd44adedb9b5a6acb96f62fa77b8c328"},"dob":{"date":"1975-06-14T19:28:39.787Z","age":46},"registered":{"date":"2003-02-20T20:31:55.660Z","age":18},"phone":"(486)-628-1291","cell":"(185)-428-9583","id":{"name":"BSN","value":"21240902"},"picture":{"large":"https://randomuser.me/api/portraits/women/65.jpg","medium":"https://randomuser.me/api/portraits/med/women/65.jpg","thumbnail":"https://randomuser.me/api/portraits/thumb/women/65.jpg"},"nat":"NL"},{"gender":"female","name":{"title":"Ms","first":"Maelya","last":"Garcia"},"location":{"street":{"number":2814,"name":"Rue de L'Abbé-Soulange-Bodin"},"city":"Montreuil","state":"Isère","country":"France","postcode":83143,"coordinates":{"latitude":"37.1230","longitude":"7.4760"},"timezone":{"offset":"+10:00","description":"Eastern Australia, Guam, Vladivostok"}},"email":"maelya.garcia@example.com","login":{"uuid":"fc68317d-e777-4fa0-b9db-0090a6daa4e2","username":"redelephant140","password":"village","salt":"50VMfHAr","md5":"a886681eeace9c18d98e7d491deacfee","sha1":"b85fd977cd81433d43d50a1eea344ceb0a5c5435","sha256":"dc2abe29c4b461b284a72610bdefb053f7482bb5ec98e3fd2ef9337b01dd5014"},"dob":{"date":"1954-07-24T18:02:02.522Z","age":67},"registered":{"date":"2004-12-08T12:37:19.313Z","age":17},"phone":"03-30-05-29-70","cell":"06-86-78-84-29","id":{"name":"INSEE","value":"2NNaN15021211 41"},"picture":{"large":"https://randomuser.me/api/portraits/women/36.jpg","medium":"https://randomuser.me/api/portraits/med/women/36.jpg","thumbnail":"https://randomuser.me/api/portraits/thumb/women/36.jpg"},"nat":"FR"},{"gender":"female","name":{"title":"Mrs","first":"Angela","last":"Moreno"},"location":{"street":{"number":4872,"name":"Avenida del Planetario"},"city":"La Palma","state":"País Vasco","country":"Spain","postcode":46138,"coordinates":{"latitude":"-37.9665","longitude":"173.7284"},"timezone":{"offset":"+5:00","description":"Ekaterinburg, Islamabad, Karachi, Tashkent"}},"email":"angela.moreno@example.com","login":{"uuid":"11e863df-8d63-4146-9e03-7fa5df4988de","username":"bluebear772","password":"solution","salt":"xZk4k0wp","md5":"3b088853576a61ec7beadd0a011a8fe8","sha1":"d972d0b1253abb34eba23262bfaef70075ae0395","sha256":"843533613b8619803ea4451407d27669a87cf4c126c07d0b1e260e3baaedfdf7"},"dob":{"date":"1965-09-05T01:36:51.226Z","age":56},"registered":{"date":"2015-07-19T15:33:41.410Z","age":6},"phone":"930-245-950","cell":"659-561-747","id":{"name":"DNI","value":"02327948-L"},"picture":{"large":"https://randomuser.me/api/portraits/women/12.jpg","medium":"https://randomuser.me/api/portraits/med/women/12.jpg","thumbnail":"https://randomuser.me/api/portraits/thumb/women/12.jpg"},"nat":"ES"},{"gender":"male","name":{"title":"Mr","first":"Jim","last":"Cruz"},"location":{"street":{"number":8600,"name":"Broadway"},"city":"Peterborough","state":"Highlands and Islands","country":"United Kingdom","postcode":"TA2 3DH","coordinates":{"latitude":"87.9236","longitude":"98.1565"},"timezone":{"offset":"+10:00","description":"Eastern Australia, Guam, Vladivostok"}},"email":"jim.cruz@example.com","login":{"uuid":"91864fa3-0226-4861-984f-c0eabdc63f19","username":"heavylion662","password":"eggplant","salt":"3lz5eJK0","md5":"9e2da673862e89f23f6f4604f04b786a","sha1":"2b0c3045ec06da1dc2ca6f4a4493e1451708e24d","sha256":"7ade3d8984e44c0bd9e938f0d3f58b98f2e3a3dcee37bca05881f912695e30ed"},"dob":{"date":"1968-09-02T15:04:43.121Z","age":53},"registered":{"date":"2012-05-26T12:43:58.463Z","age":9},"phone":"017683 04934","cell":"0751-852-781","id":{"name":"NINO","value":"KT 22 49 15 F"},"picture":{"large":"https://randomuser.me/api/portraits/men/22.jpg","medium":"https://randomuser.me/api/portraits/med/men/22.jpg","thumbnail":"https://randomuser.me/api/portraits/thumb/men/22.jpg"},"nat":"GB"},{"gender":"female","name":{"title":"Ms","first":"Anaïs","last":"Arnaud"},"location":{"street":{"number":2509,"name":"Rue de L'Abbaye"},"city":"Brest","state":"Haute-Corse","country":"France","postcode":40240,"coordinates":{"latitude":"-89.5283","longitude":"-86.8661"},"timezone":{"offset":"+4:00","description":"Abu Dhabi, Muscat, Baku, Tbilisi"}},"email":"anais.arnaud@example.com","login":{"uuid":"24226259-197b-4726-a66d-2e2f53d20b6c","username":"angrydog403","password":"meredith","salt":"BcQvSAbg","md5":"9f966e3c364d2cc5d01a15821fe54bb7","sha1":"1f0293b44ea11fc3db171f4611764a73a3f3689c","sha256":"ac8978084e75d1b9a594f93857f3b88162e62c6b082768b17a61125cc0734762"},"dob":{"date":"1980-04-28T08:06:25.487Z","age":41},"registered":{"date":"2019-03-19T18:16:50.150Z","age":2},"phone":"01-14-45-61-48","cell":"06-83-42-74-32","id":{"name":"INSEE","value":"2NNaN40026378 57"},"picture":{"large":"https://randomuser.me/api/portraits/women/19.jpg","medium":"https://randomuser.me/api/portraits/med/women/19.jpg","thumbnail":"https://randomuser.me/api/portraits/thumb/women/19.jpg"},"nat":"FR"},{"gender":"male","name":{"title":"Mr","first":"بردیا","last":"پارسا"},"location":{"street":{"number":8332,"name":"میدان جمهوری"},"city":"ارومیه","state":"خراسان جنوبی","country":"Iran","postcode":27330,"coordinates":{"latitude":"-66.2112","longitude":"-64.8209"},"timezone":{"offset":"+10:00","description":"Eastern Australia, Guam, Vladivostok"}},"email":"brdy.prs@example.com","login":{"uuid":"0478f808-f9a1-4b6b-8353-cf6e68472ed0","username":"silverpeacock887","password":"quebec","salt":"j02Gc7KV","md5":"bbbc80d8760fff0d41f6a19fa173793d","sha1":"a9f8934ed375c80447b5053ea6672c5d1a30f5cf","sha256":"e5b4663076145ae6eb13f20e0cb7755407be3bad78aa57876bb957d7c6c8840d"},"dob":{"date":"1948-02-27T17:24:01.005Z","age":73},"registered":{"date":"2017-05-30T13:02:44.166Z","age":4},"phone":"092-14145702","cell":"0940-806-0414","id":{"name":"","value":null},"picture":{"large":"https://randomuser.me/api/portraits/men/10.jpg","medium":"https://randomuser.me/api/portraits/med/men/10.jpg","thumbnail":"https://randomuser.me/api/portraits/thumb/men/10.jpg"},"nat":"IR"},{"gender":"male","name":{"title":"Mr","first":"Philip","last":"Williams"},"location":{"street":{"number":7201,"name":"Balmoral St"},"city":"Sandy Lake","state":"New Brunswick","country":"Canada","postcode":"E2B 7I3","coordinates":{"latitude":"26.8847","longitude":"1.0588"},"timezone":{"offset":"+3:30","description":"Tehran"}},"email":"philip.williams@example.com","login":{"uuid":"fe26e199-f578-4a79-b31a-79672a9ef613","username":"bigsnake246","password":"wrestling","salt":"3iT34Cle","md5":"c24eedd89353ff1b807d181b7131fda9","sha1":"d7eeee334c54e50bc1918375a3c7ff03880e2a4b","sha256":"a64a989ffe765945ad0f4816a907aa93e5190ef4a7c58130b4c5819fa62859a4"},"dob":{"date":"1973-12-19T01:58:03.023Z","age":48},"registered":{"date":"2016-12-20T01:47:02.818Z","age":5},"phone":"560-945-1025","cell":"466-996-5970","id":{"name":"","value":null},"picture":{"large":"https://randomuser.me/api/portraits/men/50.jpg","medium":"https://randomuser.me/api/portraits/med/men/50.jpg","thumbnail":"https://randomuser.me/api/portraits/thumb/men/50.jpg"},"nat":"CA"},{"gender":"female","name":{"title":"Mrs","first":"Abbie","last":"Fletcher"},"location":{"street":{"number":1818,"name":"Queen Street"},"city":"Peterborough","state":"Rutland","country":"United Kingdom","postcode":"M9X 5XG","coordinates":{"latitude":"7.2237","longitude":"150.9527"},"timezone":{"offset":"+9:30","description":"Adelaide, Darwin"}},"email":"abbie.fletcher@example.com","login":{"uuid":"4c9fc8ac-9ba6-4b69-bc6f-88f7c29cbf15","username":"purpletiger852","password":"homepage-","salt":"OZAaWQnr","md5":"e422ccd5693291c5038c8973e0e3efa2","sha1":"ad259dafc523b4432941343fafcc862ff2314ae3","sha256":"08457f7da2cdf00f8c207ed37d6233d96722e720400e44f8eac4a489f2ac357e"},"dob":{"date":"1979-12-09T09:25:07.386Z","age":42},"registered":{"date":"2013-09-30T03:39:02.526Z","age":8},"phone":"017683 55598","cell":"0748-743-212","id":{"name":"NINO","value":"SL 82 30 83 U"},"picture":{"large":"https://randomuser.me/api/portraits/women/90.jpg","medium":"https://randomuser.me/api/portraits/med/women/90.jpg","thumbnail":"https://randomuser.me/api/portraits/thumb/women/90.jpg"},"nat":"GB"},{"gender":"male","name":{"title":"Mr","first":"Nathanaël","last":"Gaillard"},"location":{"street":{"number":3111,"name":"Rue de Cuire"},"city":"Avignon","state":"Var","country":"France","postcode":23577,"coordinates":{"latitude":"43.6155","longitude":"64.6794"},"timezone":{"offset":"-3:00","description":"Brazil, Buenos Aires, Georgetown"}},"email":"nathanael.gaillard@example.com","login":{"uuid":"79882fbd-c352-4f8f-937f-f46386120a21","username":"purplefrog706","password":"alicia","salt":"x7gvx448","md5":"71ba8eaa52a58bafb8786d8a011f7b47","sha1":"70115cb51a503fd12d6256547177d911e0d672fe","sha256":"6294ff7e8be576ed617960bc09020167b7d9809bb97be2eb53050faff3af47dc"},"dob":{"date":"1995-08-31T05:25:04.648Z","age":26},"registered":{"date":"2004-07-10T20:59:11.714Z","age":17},"phone":"04-33-99-17-75","cell":"06-56-92-71-85","id":{"name":"INSEE","value":"1NNaN24856344 76"},"picture":{"large":"https://randomuser.me/api/portraits/men/80.jpg","medium":"https://randomuser.me/api/portraits/med/men/80.jpg","thumbnail":"https://randomuser.me/api/portraits/thumb/men/80.jpg"},"nat":"FR"},{"gender":"male","name":{"title":"Mr","first":"Alexander","last":"Pedersen"},"location":{"street":{"number":1857,"name":"Vægtens Kvarter"},"city":"Tisvilde","state":"Syddanmark","country":"Denmark","postcode":18506,"coordinates":{"latitude":"-1.9787","longitude":"170.8923"},"timezone":{"offset":"+6:00","description":"Almaty, Dhaka, Colombo"}},"email":"alexander.pedersen@example.com","login":{"uuid":"574ee231-74c8-4119-bb1b-ad7c170b83d8","username":"smallmouse577","password":"buffalo1","salt":"GvnMNM3f","md5":"f96e1f855d579def315c29ba945c020f","sha1":"7f966ef47bf43446d22b2ddb55aadab0102fcd71","sha256":"a46d99f355046a3958d190838f646873ddd3ed384132bef28c50b3f46b25f50a"},"dob":{"date":"1990-03-16T11:20:20.240Z","age":31},"registered":{"date":"2012-04-13T07:40:02.599Z","age":9},"phone":"54073420","cell":"59345378","id":{"name":"CPR","value":"160390-2322"},"picture":{"large":"https://randomuser.me/api/portraits/men/19.jpg","medium":"https://randomuser.me/api/portraits/med/men/19.jpg","thumbnail":"https://randomuser.me/api/portraits/thumb/men/19.jpg"},"nat":"DK"},{"gender":"male","name":{"title":"Mr","first":"Gonzalo","last":"Rubio"},"location":{"street":{"number":912,"name":"Avenida de América"},"city":"Alicante","state":"País Vasco","country":"Spain","postcode":90331,"coordinates":{"latitude":"-42.8300","longitude":"96.2172"},"timezone":{"offset":"+7:00","description":"Bangkok, Hanoi, Jakarta"}},"email":"gonzalo.rubio@example.com","login":{"uuid":"d26cd41b-0352-4564-89c3-5afdc6fca598","username":"purplemeercat797","password":"legolas","salt":"CadLE16K","md5":"8119e8ed759f24b22cfba852d195f9f5","sha1":"01bf4389ff5f1b825c8232d288c2f24a93f8f0ae","sha256":"331fcdc07622965ab1973d2f790dfa03e129da57a2ea26d0e7bd2fa602e1388f"},"dob":{"date":"1954-11-26T05:21:52.344Z","age":67},"registered":{"date":"2005-08-30T07:45:49.032Z","age":16},"phone":"975-394-633","cell":"627-217-847","id":{"name":"DNI","value":"53145111-N"},"picture":{"large":"https://randomuser.me/api/portraits/men/68.jpg","medium":"https://randomuser.me/api/portraits/med/men/68.jpg","thumbnail":"https://randomuser.me/api/portraits/thumb/men/68.jpg"},"nat":"ES"},{"gender":"female","name":{"title":"Mrs","first":"Marcia","last":"Scott"},"location":{"street":{"number":4392,"name":"W Dallas St"},"city":"Devonport","state":"Western Australia","country":"Australia","postcode":272,"coordinates":{"latitude":"-10.8460","longitude":"107.5029"},"timezone":{"offset":"+6:00","description":"Almaty, Dhaka, Colombo"}},"email":"marcia.scott@example.com","login":{"uuid":"334f8435-c437-4e28-b8d1-0b94835570a5","username":"purpledog643","password":"cherokee","salt":"WnFnlbMJ","md5":"6ded087e3a5a178eb302195402aa9470","sha1":"8f04a6ca4528d7deea676018caddae22b9c5c4a7","sha256":"80b60d20e1cffd9021fd8be075a36e6162bbadbe866d1949f593d8c455be2f36"},"dob":{"date":"1950-05-14T15:27:49.939Z","age":71},"registered":{"date":"2011-06-26T05:31:06.558Z","age":10},"phone":"01-6744-3376","cell":"0446-358-581","id":{"name":"TFN","value":"754358675"},"picture":{"large":"https://randomuser.me/api/portraits/women/59.jpg","medium":"https://randomuser.me/api/portraits/med/women/59.jpg","thumbnail":"https://randomuser.me/api/portraits/thumb/women/59.jpg"},"nat":"AU"},{"gender":"female","name":{"title":"Miss","first":"Karla","last":"Poulsen"},"location":{"street":{"number":5393,"name":"Lyøvej"},"city":"Nørrebro","state":"Midtjylland","country":"Denmark","postcode":44907,"coordinates":{"latitude":"39.3905","longitude":"-25.8525"},"timezone":{"offset":"-12:00","description":"Eniwetok, Kwajalein"}},"email":"karla.poulsen@example.com","login":{"uuid":"019025af-3127-478a-a7ee-573b6447003a","username":"happycat176","password":"central","salt":"DSId0cBv","md5":"4d372a74ad2cb2ac8c64a4d42dbb23b0","sha1":"9d6d4aeea89a906aed9d4d48a111b81de68b32e5","sha256":"22d8cc5578661813bb73ec43668721be6fa08d644a78c8f5cdf6f4a8882b94df"},"dob":{"date":"1985-04-07T06:38:04.035Z","age":36},"registered":{"date":"2004-06-15T05:56:17.676Z","age":17},"phone":"43168541","cell":"18010331","id":{"name":"CPR","value":"070485-3622"},"picture":{"large":"https://randomuser.me/api/portraits/women/44.jpg","medium":"https://randomuser.me/api/portraits/med/women/44.jpg","thumbnail":"https://randomuser.me/api/portraits/thumb/women/44.jpg"},"nat":"DK"},{"gender":"male","name":{"title":"Mr","first":"بردیا","last":"احمدی"},"location":{"street":{"number":3905,"name":"سمیه"},"city":"اصفهان","state":"البرز","country":"Iran","postcode":81849,"coordinates":{"latitude":"-35.6428","longitude":"92.1561"},"timezone":{"offset":"-4:00","description":"Atlantic Time (Canada), Caracas, La Paz"}},"email":"brdy.hmdy@example.com","login":{"uuid":"d8fb34cf-db14-432f-980f-9cbbbe1d1e32","username":"blueostrich167","password":"farmer","salt":"tMIabrW9","md5":"1082f99acc3f1946086e67fb3518e147","sha1":"13356fdfa55da82f4042953fb004b025ea8b4c4d","sha256":"aa38761ad781efb55e1f07bd1ba8c0534eb9b0b5c6b3fc80bec3023bd3f00dff"},"dob":{"date":"1992-09-30T21:33:33.492Z","age":29},"registered":{"date":"2005-12-15T07:25:10.294Z","age":16},"phone":"045-19111979","cell":"0934-564-2426","id":{"name":"","value":null},"picture":{"large":"https://randomuser.me/api/portraits/men/16.jpg","medium":"https://randomuser.me/api/portraits/med/men/16.jpg","thumbnail":"https://randomuser.me/api/portraits/thumb/men/16.jpg"},"nat":"IR"},{"gender":"male","name":{"title":"Mr","first":"George","last":"Soto"},"location":{"street":{"number":4133,"name":"Springfield Road"},"city":"Edenderry","state":"Carlow","country":"Ireland","postcode":62554,"coordinates":{"latitude":"-5.3627","longitude":"-139.5033"},"timezone":{"offset":"-7:00","description":"Mountain Time (US & Canada)"}},"email":"george.soto@example.com","login":{"uuid":"79c0370e-0a17-4162-9cf9-b2b46e2bee72","username":"bluebutterfly949","password":"akira","salt":"j9F4hNbZ","md5":"8ba5e2c256616fcb4a5397b60bdb09bc","sha1":"1caea77f44a26aea9334ea971d3a5b5dc0ef9b19","sha256":"b115f978f5aadca5e1031246eac625364ba153a2e544110ee9be790c1f170f1e"},"dob":{"date":"1986-09-07T08:48:01.260Z","age":35},"registered":{"date":"2015-06-27T01:05:51.772Z","age":6},"phone":"051-870-6821","cell":"081-038-4178","id":{"name":"PPS","value":"7524241T"},"picture":{"large":"https://randomuser.me/api/portraits/men/18.jpg","medium":"https://randomuser.me/api/portraits/med/men/18.jpg","thumbnail":"https://randomuser.me/api/portraits/thumb/men/18.jpg"},"nat":"IE"},{"gender":"male","name":{"title":"Mr","first":"Léo","last":"Lacroix"},"location":{"street":{"number":7427,"name":"Place du 22 Novembre 1943"},"city":"Vitry-sur-Seine","state":"Corrèze","country":"France","postcode":42121,"coordinates":{"latitude":"-76.2743","longitude":"172.9902"},"timezone":{"offset":"+3:30","description":"Tehran"}},"email":"leo.lacroix@example.com","login":{"uuid":"1d28d88a-0f79-4204-9799-fe99ec0241c5","username":"sadgorilla819","password":"gotribe","salt":"gcf2L5Qc","md5":"6679ff0192180520486fca93800f5f0a","sha1":"4debb65e52df7a8926bb523b985e4488b060f941","sha256":"99fb91e8e96f7c3097aef29851c1067bcbf5e646f3ceb606beca060523635c65"},"dob":{"date":"1985-02-01T11:04:38.808Z","age":36},"registered":{"date":"2003-12-01T21:43:23.710Z","age":18},"phone":"02-97-72-00-72","cell":"06-30-78-72-91","id":{"name":"INSEE","value":"1NNaN74977317 41"},"picture":{"large":"https://randomuser.me/api/portraits/men/0.jpg","medium":"https://randomuser.me/api/portraits/med/men/0.jpg","thumbnail":"https://randomuser.me/api/portraits/thumb/men/0.jpg"},"nat":"FR"},{"gender":"female","name":{"title":"Ms","first":"Terumi","last":"Farias"},"location":{"street":{"number":4181,"name":"Avenida D. Pedro Ii"},"city":"Valparaíso de Goiás","state":"Espírito Santo","country":"Brazil","postcode":77232,"coordinates":{"latitude":"-23.3018","longitude":"16.4255"},"timezone":{"offset":"+1:00","description":"Brussels, Copenhagen, Madrid, Paris"}},"email":"terumi.farias@example.com","login":{"uuid":"b047e2aa-cead-460c-a347-9edaaecfc1fc","username":"whitefrog484","password":"testing","salt":"K8lrbXpc","md5":"a88213495370b8b52e516b62bcfdeccf","sha1":"12926364ac8cf12cf7a13a95594c2204017de027","sha256":"063afb1d7096975b655098d66fb771181583625bc88b8a31cbf1ce4677ec0bdf"},"dob":{"date":"1972-10-10T17:32:47.108Z","age":49},"registered":{"date":"2014-12-23T17:00:18.244Z","age":7},"phone":"(07) 0539-0032","cell":"(49) 9010-1838","id":{"name":"","value":null},"picture":{"large":"https://randomuser.me/api/portraits/women/82.jpg","medium":"https://randomuser.me/api/portraits/med/women/82.jpg","thumbnail":"https://randomuser.me/api/portraits/thumb/women/82.jpg"},"nat":"BR"}],"info":{"seed":"5ef82f2488c34074","results":20,"page":1,"version":"1.3"}}